{
  "collectionName": "components_sections_section_widget_forms",
  "info": {
    "name": "sectionWidgetForm",
    "icon": "arrow-circle-up"
  },
  "options": {},
  "attributes": {
    "description": {
      "type": "text"
    },
    "picture": {
      "model": "file",
      "via": "related",
      "allowedTypes": [
        "images",
        "files",
        "videos"
      ],
      "plugin": "upload",
      "required": false,
      "pluginOptions": {}
    },
    "form": {
      "type": "component",
      "repeatable": false,
      "component": "formulario.form"
    }
  }
}
